perfact/__init__.py
perfact/zodbsync/__init__.py
perfact/zodbsync/extedit.py
perfact/zodbsync/helpers.py
perfact/zodbsync/main.py
perfact/zodbsync/object_mixins.py
perfact/zodbsync/object_types.py
perfact/zodbsync/scripts.py
perfact/zodbsync/subcommand.py
perfact/zodbsync/zodbsync.py
perfact/zodbsync/commands/__init__.py
perfact/zodbsync/commands/checkout.py
perfact/zodbsync/commands/execute.py
perfact/zodbsync/commands/fastforward.py
perfact/zodbsync/commands/freeze.py
perfact/zodbsync/commands/layer_init.py
perfact/zodbsync/commands/layer_update.py
perfact/zodbsync/commands/pick.py
perfact/zodbsync/commands/playback.py
perfact/zodbsync/commands/record.py
perfact/zodbsync/commands/reformat.py
perfact/zodbsync/commands/reset.py
perfact/zodbsync/commands/upload.py
perfact/zodbsync/commands/watch.py
perfact/zodbsync/commands/with_lock.py
perfact/zodbsync/tests/__init__.py
perfact/zodbsync/tests/environment.py
perfact/zodbsync/tests/test_helpers.py
perfact/zodbsync/tests/test_sync.py
perfact_zodbsync-26.1.0.dist-info/licenses/LICENSE.txt
perfact_zodbsync-26.1.0.dist-info/METADATA
perfact_zodbsync-26.1.0.dist-info/WHEEL
perfact_zodbsync-26.1.0.dist-info/entry_points.txt
perfact_zodbsync-26.1.0.dist-info/top_level.txt
perfact_zodbsync-26.1.0.dist-info/RECORD
