Metadata-Version: 2.4
Name: perfact-zodbsync
Version: 26.1.0
Summary: Synchronize ZODB objects with a file system structure
Author-email: Ján Jockusch <jan.jockusch@perfact.de>, Viktor Dick <viktor.dick@perfact.de>
Project-URL: Homepage, https://github.com/perfact/zodbsync
Classifier: Programming Language :: Python :: 3
Classifier: License :: OSI Approved :: GNU General Public License v2 (GPLv2)
Classifier: Operating System :: POSIX :: Linux
Classifier: Framework :: Zope
Classifier: Topic :: Software Development :: Version Control :: Git
Requires-Python: >=3.8
License-File: LICENSE.txt
Requires-Dist: filelock
Requires-Dist: ZODB
Requires-Dist: Zope
Dynamic: license-file
